{
  "autoRotateColliderBox": true,
  "collideEntity": 1,
  "collider": {
    "extent": {
      "x": 1.5,
      "y": 1.5,
      "z": 1.5
    },
    "height": 0,
    "radius": 0,
    "rotation": {
      "x": 0,
      "y": 0,
      "z": 0
    },
    "type": "Box"
  },
  "collisionGroup": 16,
  "followTarget": false,
  "gravity": 0,
  "hitEntityCount": 1,
  "hitEntitySkill": "myplugin/gen_skill/damage_skill_37034",
  "hitInterval": 99,
  "lifeTime": 20,
  "moveAcc": 0,
  "moveSpeed": 1.8,
  "rotateSpeed": 0,
  "skillId": 37034,
  "startEffect": {
    "effect": "g2069_skill_mingren_c2.effect",
    "pos": {
      "x": 0,
      "y": 1,
      "z": 0
    },
    "scale": {
      "x": 1,
      "y": 1,
      "z": 1
    }
  },
  "vanishOnHitPart": true,
  "vanishSkill": "myplugin/gen_skill/skill_370341",
  "vanishTime": 0
}