{
  "bake_texture_size": 64,
  "blinn": 0,
  "canBreak": true,
  "hdr": 0,
  "hideCloud": true,
  "is_bake_light_effect_visible": false,
  "moveDownGravity": 0.15,
  "scene": [
    {
      "attributes": [],
      "class": "VoxelTerrain",
      "customProperties": [],
      "properties": {
        "collisionGroup": "1",
        "id": "9106575671146840065",
        "isVisible": "true",
        "name": "VoxelTerrain",
        "uniqueKey": "",
        "useForCollision": "false"
      }
    },
    {
      "attributes": [],
      "class": "Light",
      "customProperties": [],
      "properties": {
        "bakeTextureWeight": "1",
        "batchType": "Static",
        "canAcceptShadow": "true",
        "canGenerateShadow": "true",
        "colorFrame": "0:ff7f838b,1439:ff7f838b",
        "colorFrame2": "0:ff3d3a35,1439:ff3d3a35",
        "customViewDistance": "nil",
        "dayMode": "AllDay",
        "id": "9106575671212703745",
        "ID": "13",
        "intensityFrame": "0:1,1439:1",
        "isVisible": "true",
        "lightActived": "true",
        "lightAngle": "30.0",
        "lightBrightness": "0.5",
        "lightColor": "r:1.0 g:1.0 b:1.0 a:1.0",
        "lightLength": "1.0",
        "lightMode": "RealTime",
        "lightRange": "8.0",
        "lightType": "GlobalLight",
        "lightWidth": "1.0",
        "name": "EnvironmentLight",
        "needSync": "false",
        "position": "x:0 y:0 z:0",
        "renderMode": "Pixel",
        "rotation": "x:0 y:0 z:0",
        "scale": "x:1 y:1 z:1",
        "selectable": "true",
        "shadowsDistance": "20.0",
        "shadowsIntensity": "1.0",
        "shadowsOffset": "0.02",
        "shadowsPresicion": "1024",
        "shadowsType": "null",
        "skyColor": "r:0.996078431372549 g:0.980392156862745 b:0.96078431372549 a:1.0",
        "skyLineColor": "r:0.737254901960784 g:0.909803921568627 b:0.913725490196078 a:1.0",
        "templateId": "9106575671212703745",
        "useAnchor": "true",
        "useForCollision": "false",
        "viewDistance": "nil"
      }
    },
    {
      "attributes": [],
      "class": "Light",
      "customProperties": [],
      "properties": {
        "bakeTextureWeight": "1",
        "batchType": "Static",
        "canAcceptShadow": "true",
        "canGenerateShadow": "true",
        "colorFrame": "0:ffffffff,1439:ffffffff",
        "colorFrame2": "0:ff3d3a35,1439:ff3d3a35",
        "customViewDistance": "nil",
        "dayMode": "AllDay",
        "id": "9106575671302569985",
        "ID": "14",
        "intensityFrame": "0:3,720:8,900:8,1439:2",
        "isVisible": "true",
        "lightActived": "true",
        "lightAngle": "30.0",
        "lightBrightness": "0.6",
        "lightColor": "r:0.984313725490196 g:0.945098039215686 b:0.937254901960784 a:1.0",
        "lightLength": "1.0",
        "lightMode": "RealTime",
        "lightRange": "8.0",
        "lightType": "DirectionalLight",
        "lightWidth": "1.0",
        "name": "DirectionalLight",
        "needSync": "false",
        "position": "x:0 y:5 z:0",
        "renderMode": "Pixel",
        "rotation": "x:-46.9998817443848 y:2.13589755730936e-05 z:28.9999713897705",
        "rotationFrame": "0:0,720:-90,1439:0;0:0,1439:0;0:0,1439:0",
        "scale": "x:1 y:1 z:1",
        "selectable": "true",
        "shadowsDistance": "512",
        "shadowsIntensity": "1.0",
        "shadowsOffset": "0.02",
        "shadowsPresicion": "1024",
        "shadowsType": "soft",
        "skyColor": "r:0.498039215686275 g:0.513725490196078 b:0.545098039215686 a:1.0",
        "skyLineColor": "r:0.23921568627451 g:0.227450980392157 b:0.207843137254902 a:1.0",
        "templateId": "9106575671302569985",
        "useAnchor": "true",
        "useForCollision": "false",
        "viewDistance": "nil"
      }
    },
    {
      "attributes": [],
      "class": "CameraNode",
      "customProperties": [],
      "properties": {
        "cameraSize": "5",
        "exposure": "0",
        "farPlane": "1000",
        "fov": "65",
        "gamma": "1.0",
        "id": "9106575671406592001",
        "isVisible": "true",
        "maxDetectionDistance": "30",
        "name": "CameraNode",
        "nearPlane": "0.3",
        "occlusionCulling": "false",
        "projectionMode": "0",
        "toneMappingMode": "0",
        "useForCollision": "false",
        "useHdr": "0"
      }
    },
    {
      "attributes": [],
      "children": [
        {
          "attributes": [],
          "class": "MeshPart",
          "customProperties": [],
          "properties": {
            "btsKey": "",
            "canAcceptShadow": "true",
            "canGenerateShadow": "true",
            "customShapeData": "",
            "density": "2.2",
            "discardAlpha": "0.0",
            "exists_baked_data": "false",
            "friction": "0.37",
            "id": "9112275351005446145",
            "lodData": {
              "lodModelItem": []
            },
            "massCenter": "x:68.0960159301758 y:-14.1285123825073 z:-46.0189895629883",
            "materialAlpha": "1.0",
            "materialColor": "r:1.0 g:1.0 b:1.0 a:1.0",
            "materialOffset": "x:1 y:1 z:1.0",
            "mesh": "asset/scene/map_icebergvillage/g2069_icebergvillage_plants02.mesh",
            "name": "g2069_icebergvillage_plants02.mesh",
            "needSync": "false",
            "partNavMeshType": "1",
            "position": "x:68.0960159301758 y:-14.1285123825073 z:-46.0189895629883",
            "restitution": "0.3",
            "rotation": "x:0 y:0 z:0",
            "simpleEmissiveIntensity": "1.0",
            "staticBatchNo": "1",
            "templateId": "9112275351005446145",
            "useAnchor": "true",
            "useForCollision": "false"
          }
        },
        {
          "attributes": [],
          "class": "MeshPart",
          "customProperties": [],
          "properties": {
            "btsKey": "",
            "canAcceptShadow": "true",
            "canGenerateShadow": "true",
            "customShapeData": "",
            "density": "2.2",
            "discardAlpha": "0.0",
            "exists_baked_data": "false",
            "friction": "0.37",
            "id": "9115062433663336449",
            "lodData": {
              "lodModelItem": []
            },
            "massCenter": "x:24.0341911315918 y:2.71984338760376 z:-48.5209350585938",
            "materialAlpha": "1.0",
            "materialColor": "r:1.0 g:1.0 b:1.0 a:1.0",
            "materialOffset": "x:1 y:1 z:1.0",
            "mesh": "asset/scene/map_icebergvillage/map_icebergvillage_fangwu_03.mesh",
            "name": "map_icebergvillage_fangwu_03.mesh",
            "needSync": "false",
            "partNavMeshType": "1",
            "position": "x:24.0341911315918 y:2.71984338760376 z:-48.5209350585938",
            "restitution": "0.3",
            "rotation": "x:0 y:-69.0000076293945 z:0",
            "scale": "x:1.5 y:1.5 z:1.5",
            "simpleEmissiveIntensity": "1.0",
            "staticBatchNo": "1",
            "templateId": "9115062433663336449",
            "useAnchor": "true",
            "useForCollision": "false"
          }
        },
        {
          "attributes": [],
          "class": "MeshPart",
          "customProperties": [],
          "properties": {
            "btsKey": "",
            "canAcceptShadow": "true",
            "canGenerateShadow": "true",
            "customShapeData": "",
            "density": "2.2",
            "discardAlpha": "0.0",
            "exists_baked_data": "false",
            "friction": "0.37",
            "id": "9119356207578234881",
            "lodData": {
              "lodModelItem": []
            },
            "massCenter": "x:-2.90846872329712 y:-28.2 z:0.284864723682404",
            "materialAlpha": "0.5",
            "materialColor": "r:1.0 g:1.0 b:1.0 a:1.0",
            "materialOffset": "x:1 y:1 z:1.0",
            "mesh": "asset/scene/map_icebergvillage/g2069_icebergvillage_water.mesh",
            "name": "g2069_icebergvillage_water.mesh",
            "needSync": "false",
            "originAnchor": "true",
            "partNavMeshType": "1",
            "position": "x:-2.90846872329712 y:-28.2 z:0.284864723682404",
            "restitution": "0.3",
            "rotation": "x:0 y:0 z:0",
            "simpleEmissiveIntensity": "1.0",
            "templateId": "9119356207578234881",
            "useAnchor": "true",
            "useCollide": "false",
            "useForCollision": "false"
          }
        },
        {
          "attributes": [],
          "class": "MeshPart",
          "customProperties": [],
          "properties": {
            "btsKey": "",
            "canAcceptShadow": "true",
            "canGenerateShadow": "true",
            "customShapeData": "",
            "density": "2.2",
            "discardAlpha": "0.0",
            "exists_baked_data": "false",
            "friction": "0.37",
            "id": "9112250799103295489",
            "lodData": {
              "lodModelItem": []
            },
            "massCenter": "x:-32.9099998474121 y:-15.3645009994507 z:-65.2050247192383",
            "materialAlpha": "1.0",
            "materialColor": "r:1.0 g:1.0 b:1.0 a:1.0",
            "materialOffset": "x:1 y:1 z:1.0",
            "mesh": "asset/scene/map_icebergvillage/g2069_icebergvillage_plants02.mesh",
            "name": "g2069_icebergvillage_plants02.mesh",
            "needSync": "false",
            "partNavMeshType": "1",
            "position": "x:-32.9099998474121 y:-15.3645009994507 z:-65.2050247192383",
            "restitution": "0.3",
            "rotation": "x:0 y:0 z:0",
            "scale": "x:0.799999 y:0.799999 z:0.799999",
            "simpleEmissiveIntensity": "1.0",
            "staticBatchNo": "1",
            "templateId": "9112250799103295489",
            "useAnchor": "true",
            "useForCollision": "false"
          }
        },
        {
          "attributes": [],
          "class": "MeshPart",
          "customProperties": [],
          "properties": {
            "btsKey": "",
            "canAcceptShadow": "true",
            "canGenerateShadow": "true",
            "customShapeData": "",
            "density": "2.2",
            "discardAlpha": "0.0",
            "exists_baked_data": "false",
            "friction": "0.37",
            "id": "9112238368297156609",
            "lodData": {
              "lodModelItem": []
            },
            "massCenter": "x:-43.7999954223633 y:14.8795003890991 z:46.3589935302734",
            "materialAlpha": "1.0",
            "materialColor": "r:1.0 g:1.0 b:1.0 a:1.0",
            "materialOffset": "x:1 y:1 z:1.0",
            "mesh": "asset/scene/map_icebergvillage/g2069_icebergvillage_plants02.mesh",
            "name": "g2069_icebergvillage_plants02.mesh",
            "needSync": "false",
            "partNavMeshType": "1",
            "position": "x:-43.7999954223633 y:14.8795003890991 z:46.3589935302734",
            "restitution": "0.3",
            "rotation": "x:0 y:0 z:0",
            "simpleEmissiveIntensity": "1.0",
            "staticBatchNo": "1",
            "templateId": "9112238368297156609",
            "useAnchor": "true",
            "useForCollision": "false"
          }
        },
        {
          "attributes": [],
          "class": "MeshPart",
          "customProperties": [],
          "properties": {
            "btsKey": "",
            "canAcceptShadow": "true",
            "canGenerateShadow": "true",
            "customShapeData": "",
            "density": "2.2",
            "discardAlpha": "0.0",
            "exists_baked_data": "false",
            "friction": "0.37",
            "id": "9112238967245258753",
            "lodData": {
              "lodModelItem": []
            },
            "massCenter": "x:-92.8651962280273 y:27.3103046417236 z:50.6204833984375",
            "materialAlpha": "1.0",
            "materialColor": "r:1.0 g:1.0 b:1.0 a:1.0",
            "materialOffset": "x:1 y:1 z:1.0",
            "mesh": "asset/scene/map_icebergvillage/g2069_icebergvillage_plants01.mesh",
            "name": "g2069_icebergvillage_plants01.mesh",
            "needSync": "false",
            "partNavMeshType": "1",
            "position": "x:-92.8651962280273 y:27.3103046417236 z:50.6204833984375",
            "restitution": "0.3",
            "rotation": "x:0 y:-43 z:0",
            "scale": "x:1.5 y:1.5 z:1.5",
            "simpleEmissiveIntensity": "1.0",
            "staticBatchNo": "1",
            "templateId": "9112238967245258753",
            "useAnchor": "true",
            "useForCollision": "false"
          }
        },
        {
          "attributes": [],
          "class": "MeshPart",
          "customProperties": [],
          "properties": {
            "btsKey": "",
            "canAcceptShadow": "true",
            "canGenerateShadow": "true",
            "customShapeData": "",
            "density": "2.2",
            "discardAlpha": "0.0",
            "exists_baked_data": "false",
            "friction": "0.37",
            "id": "9115062371939352577",
            "lodData": {
              "lodModelItem": []
            },
            "massCenter": "x:-6.6700005531311 y:2.12664985656738 z:-38.1330070495605",
            "materialAlpha": "1.0",
            "materialColor": "r:1.0 g:1.0 b:1.0 a:1.0",
            "materialOffset": "x:1 y:1 z:1.0",
            "mesh": "asset/scene/map_icebergvillage/map_icebergvillage_fangwu_01.mesh",
            "name": "map_icebergvillage_fangwu_01.mesh",
            "needSync": "false",
            "partNavMeshType": "1",
            "position": "x:-6.6700005531311 y:2.12664985656738 z:-38.1330070495605",
            "restitution": "0.3",
            "rotation": "x:0 y:180 z:0",
            "scale": "x:1.5 y:1.5 z:1.5",
            "simpleEmissiveIntensity": "1.0",
            "templateId": "9115062371939352577",
            "useAnchor": "true",
            "useForCollision": "false"
          }
        },
        {
          "attributes": [],
          "class": "MeshPart",
          "customProperties": [],
          "properties": {
            "btsKey": "",
            "canAcceptShadow": "true",
            "canGenerateShadow": "true",
            "customShapeData": "",
            "density": "2.2",
            "discardAlpha": "0.0",
            "exists_baked_data": "false",
            "friction": "0.37",
            "id": "9112247957668528129",
            "lodData": {
              "lodModelItem": []
            },
            "massCenter": "x:49.6710090637207 y:6.37029838562012 z:-31.7869873046875",
            "materialAlpha": "1.0",
            "materialColor": "r:1.0 g:1.0 b:1.0 a:1.0",
            "materialOffset": "x:1 y:1 z:1.0",
            "mesh": "asset/scene/map_icebergvillage/g2069_icebergvillage_plants01.mesh",
            "name": "g2069_icebergvillage_plants01.mesh",
            "needSync": "false",
            "partNavMeshType": "1",
            "position": "x:49.6710090637207 y:6.37029838562012 z:-31.7869873046875",
            "restitution": "0.3",
            "rotation": "x:0 y:180 z:0",
            "simpleEmissiveIntensity": "1.0",
            "staticBatchNo": "1",
            "templateId": "9112247957668528129",
            "useAnchor": "true",
            "useForCollision": "false"
          }
        },
        {
          "attributes": [],
          "class": "MeshPart",
          "customProperties": [],
          "properties": {
            "btsKey": "",
            "canAcceptShadow": "true",
            "canGenerateShadow": "true",
            "customShapeData": "",
            "density": "2.2",
            "discardAlpha": "0.0",
            "exists_baked_data": "false",
            "friction": "0.37",
            "id": "9115067411309658113",
            "lodData": {
              "lodModelItem": []
            },
            "massCenter": "x:34.0640029907227 y:19.3148555755615 z:-14.8600091934204",
            "materialAlpha": "1.0",
            "materialColor": "r:1.0 g:1.0 b:1.0 a:1.0",
            "materialOffset": "x:1 y:1 z:1.0",
            "mesh": "asset/scene/map_icebergvillage/map_icebergvillage_fangwu_03.mesh",
            "name": "map_icebergvillage_fangwu_03.mesh",
            "needSync": "false",
            "partNavMeshType": "1",
            "position": "x:34.0640029907227 y:19.3148555755615 z:-14.8600091934204",
            "restitution": "0.3",
            "rotation": "x:0 y:-90 z:0",
            "scale": "x:1.5 y:1.5 z:1.5",
            "simpleEmissiveIntensity": "1.0",
            "staticBatchNo": "1",
            "templateId": "9115067411309658113",
            "useAnchor": "true",
            "useForCollision": "false"
          }
        },
        {
          "attributes": [],
          "class": "MeshPart",
          "customProperties": [],
          "properties": {
            "btsKey": "",
            "canAcceptShadow": "true",
            "canGenerateShadow": "true",
            "customShapeData": "",
            "density": "2.2",
            "discardAlpha": "0.0",
            "exists_baked_data": "false",
            "friction": "0.37",
            "id": "9112271631750660097",
            "lodData": {
              "lodModelItem": []
            },
            "massCenter": "x:-61.2719955444336 y:6.23429298400879 z:-0.388003349304199",
            "materialAlpha": "1.0",
            "materialColor": "r:1.0 g:1.0 b:1.0 a:1.0",
            "materialOffset": "x:1 y:1 z:1.0",
            "mesh": "asset/scene/map_icebergvillage/g2069_icebergvillage_plants01.mesh",
            "name": "g2069_icebergvillage_plants01.mesh",
            "needSync": "false",
            "partNavMeshType": "1",
            "position": "x:-61.2719955444336 y:6.23429298400879 z:-0.388003349304199",
            "restitution": "0.3",
            "rotation": "x:0 y:90 z:0",
            "simpleEmissiveIntensity": "1.0",
            "staticBatchNo": "1",
            "templateId": "9112271631750660097",
            "useAnchor": "true",
            "useForCollision": "false"
          }
        },
        {
          "attributes": [],
          "class": "MeshPart",
          "customProperties": [],
          "properties": {
            "btsKey": "",
            "canAcceptShadow": "true",
            "canGenerateShadow": "true",
            "customShapeData": "",
            "density": "2.2",
            "discardAlpha": "0.0",
            "exists_baked_data": "false",
            "friction": "0.37",
            "id": "9112276365802602497",
            "lodData": {
              "lodModelItem": []
            },
            "massCenter": "x:34.7820930480957 y:-21.0439281463623 z:-64.6391754150391",
            "materialAlpha": "1.0",
            "materialColor": "r:1.0 g:1.0 b:1.0 a:1.0",
            "materialOffset": "x:1 y:1 z:1.0",
            "mesh": "asset/scene/map_icebergvillage/g2069_icebergvillage_plants03.mesh",
            "name": "g2069_icebergvillage_plants03.mesh",
            "needSync": "false",
            "partNavMeshType": "1",
            "position": "x:34.7820930480957 y:-21.0439281463623 z:-64.6391754150391",
            "restitution": "0.3",
            "rotation": "x:0 y:115.999992370605 z:0",
            "scale": "x:1.2 y:1.2 z:1.2",
            "simpleEmissiveIntensity": "1.0",
            "staticBatchNo": "1",
            "templateId": "9112276365802602497",
            "useAnchor": "true",
            "useForCollision": "false"
          }
        },
        {
          "attributes": [],
          "class": "MeshPart",
          "customProperties": [],
          "properties": {
            "btsKey": "",
            "canAcceptShadow": "true",
            "canGenerateShadow": "true",
            "customShapeData": "",
            "density": "2.2",
            "discardAlpha": "0.0",
            "exists_baked_data": "false",
            "friction": "0.37",
            "id": "9112237481963438081",
            "lodData": {
              "lodModelItem": []
            },
            "massCenter": "x:87.8389587402344 y:27.6544971466064 z:8.89400386810303",
            "materialAlpha": "1.0",
            "materialColor": "r:1.0 g:1.0 b:1.0 a:1.0",
            "materialOffset": "x:1 y:1 z:1.0",
            "mesh": "asset/scene/map_icebergvillage/g2069_icebergvillage_plants02.mesh",
            "name": "g2069_icebergvillage_plants02.mesh",
            "needSync": "false",
            "partNavMeshType": "1",
            "position": "x:87.8389587402344 y:27.6544971466064 z:8.89400386810303",
            "restitution": "0.3",
            "rotation": "x:0 y:0 z:0",
            "scale": "x:0.799999 y:0.799999 z:0.799999",
            "simpleEmissiveIntensity": "1.0",
            "staticBatchNo": "1",
            "templateId": "9112237481963438081",
            "useAnchor": "true",
            "useForCollision": "false"
          }
        },
        {
          "attributes": [],
          "class": "MeshPart",
          "customProperties": [],
          "properties": {
            "btsKey": "",
            "canAcceptShadow": "true",
            "canGenerateShadow": "true",
            "customShapeData": "",
            "density": "2.2",
            "discardAlpha": "0.0",
            "exists_baked_data": "false",
            "friction": "0.37",
            "id": "9112239662139867137",
            "lodData": {
              "lodModelItem": []
            },
            "massCenter": "x:-65.1810150146484 y:-0.876968383789062 z:-11.987006187439",
            "materialAlpha": "1.0",
            "materialColor": "r:1.0 g:1.0 b:1.0 a:1.0",
            "materialOffset": "x:1 y:1 z:1.0",
            "mesh": "asset/scene/map_icebergvillage/g2069_icebergvillage_plants03.mesh",
            "name": "g2069_icebergvillage_plants03.mesh",
            "needSync": "false",
            "partNavMeshType": "1",
            "position": "x:-65.1810150146484 y:-0.876968383789062 z:-11.987006187439",
            "restitution": "0.3",
            "rotation": "x:0 y:90 z:0",
            "simpleEmissiveIntensity": "1.0",
            "staticBatchNo": "1",
            "templateId": "9112239662139867137",
            "useAnchor": "true",
            "useForCollision": "false"
          }
        },
        {
          "attributes": [],
          "class": "MeshPart",
          "customProperties": [],
          "properties": {
            "btsKey": "",
            "canAcceptShadow": "true",
            "canGenerateShadow": "true",
            "customShapeData": "",
            "density": "2.2",
            "discardAlpha": "0.0",
            "exists_baked_data": "false",
            "friction": "0.37",
            "id": "9112212433854644225",
            "lodData": {
              "lodModelItem": []
            },
            "massCenter": "x:-2.9084997177124 y:-6.64106369018555 z:0.284864723682404",
            "materialAlpha": "1.0",
            "materialColor": "r:1.0 g:1.0 b:1.0 a:1.0",
            "materialOffset": "x:1 y:1 z:1.0",
            "mesh": "asset/scene/map_icebergvillage/g2069_icebergvillage.mesh",
            "name": "g2069_icebergvillage.mesh",
            "needSync": "false",
            "originAnchor": "true",
            "partNavMeshType": "1",
            "position": "x:-2.9084997177124 y:-6.64106369018555 z:0.284864723682404",
            "restitution": "0.3",
            "rotation": "x:0 y:0 z:0",
            "selectable": "true",
            "simpleEmissiveIntensity": "1.0",
            "templateId": "9112212433854644225",
            "useAnchor": "true",
            "useForCollision": "false"
          }
        },
        {
          "attributes": [],
          "class": "MeshPart",
          "customProperties": [],
          "properties": {
            "btsKey": "",
            "canAcceptShadow": "true",
            "canGenerateShadow": "true",
            "customShapeData": "",
            "density": "2.2",
            "discardAlpha": "0.0",
            "exists_baked_data": "false",
            "friction": "0.37",
            "id": "9112244798870175745",
            "lodData": {
              "lodModelItem": []
            },
            "massCenter": "x:13.5250015258789 y:10.3312959671021 z:-27.9240074157715",
            "materialAlpha": "1.0",
            "materialColor": "r:1.0 g:1.0 b:1.0 a:1.0",
            "materialOffset": "x:1 y:1 z:1.0",
            "mesh": "asset/scene/map_icebergvillage/g2069_icebergvillage_plants01.mesh",
            "name": "g2069_icebergvillage_plants01.mesh",
            "needSync": "false",
            "partNavMeshType": "1",
            "position": "x:13.5250015258789 y:10.3312959671021 z:-27.9240074157715",
            "restitution": "0.3",
            "rotation": "x:0 y:0 z:0",
            "scale": "x:1.5 y:1.5 z:1.5",
            "simpleEmissiveIntensity": "1.0",
            "staticBatchNo": "1",
            "templateId": "9112244798870175745",
            "useAnchor": "true",
            "useForCollision": "false"
          }
        },
        {
          "attributes": [],
          "class": "MeshPart",
          "customProperties": [],
          "properties": {
            "btsKey": "",
            "canAcceptShadow": "true",
            "canGenerateShadow": "true",
            "customShapeData": "",
            "density": "2.2",
            "discardAlpha": "0.0",
            "exists_baked_data": "false",
            "friction": "0.37",
            "id": "9115062405965152257",
            "lodData": {
              "lodModelItem": []
            },
            "massCenter": "x:-67.5839920043945 y:12.0267429351807 z:35.2698249816895",
            "materialAlpha": "1.0",
            "materialColor": "r:1.0 g:1.0 b:1.0 a:1.0",
            "materialOffset": "x:1 y:1 z:1.0",
            "mesh": "asset/scene/map_icebergvillage/map_icebergvillage_fangwu_02.mesh",
            "name": "map_icebergvillage_fangwu_02.mesh",
            "needSync": "false",
            "partNavMeshType": "1",
            "position": "x:-67.5839920043945 y:12.0267429351807 z:35.2698249816895",
            "restitution": "0.3",
            "rotation": "x:0 y:101 z:0",
            "scale": "x:1.5 y:1.5 z:1.5",
            "simpleEmissiveIntensity": "1.0",
            "staticBatchNo": "1",
            "templateId": "9115062405965152257",
            "useAnchor": "true",
            "useForCollision": "false"
          }
        },
        {
          "attributes": [],
          "class": "MeshPart",
          "customProperties": [],
          "properties": {
            "btsKey": "",
            "canAcceptShadow": "true",
            "canGenerateShadow": "true",
            "customShapeData": "",
            "density": "2.2",
            "discardAlpha": "0.0",
            "exists_baked_data": "false",
            "friction": "0.37",
            "id": "9112448743943323649",
            "lodData": {
              "lodModelItem": []
            },
            "massCenter": "x:-28.5537605285645 y:-20.9377765655518 z:-64.8181838989258",
            "materialAlpha": "1.0",
            "materialColor": "r:1.0 g:1.0 b:1.0 a:1.0",
            "materialOffset": "x:1 y:1 z:1.0",
            "mesh": "asset/scene/map_icebergvillage/g2069_icebergvillage_stone01.mesh",
            "name": "g2069_icebergvillage_stone01.mesh",
            "needSync": "false",
            "partNavMeshType": "1",
            "position": "x:-28.5537605285645 y:-20.9377765655518 z:-64.8181838989258",
            "restitution": "0.3",
            "rotation": "x:0 y:142 z:0",
            "simpleEmissiveIntensity": "1.0",
            "staticBatchNo": "1",
            "templateId": "9112448743943323649",
            "useAnchor": "true",
            "useForCollision": "false"
          }
        },
        {
          "attributes": [],
          "class": "MeshPart",
          "customProperties": [],
          "properties": {
            "btsKey": "",
            "canAcceptShadow": "true",
            "canGenerateShadow": "true",
            "customShapeData": "",
            "density": "2.2",
            "discardAlpha": "0.0",
            "exists_baked_data": "false",
            "friction": "0.37",
            "id": "9115066156583518209",
            "lodData": {
              "lodModelItem": []
            },
            "massCenter": "x:73.329948425293 y:26.9676609039307 z:10.810959815979",
            "materialAlpha": "1.0",
            "materialColor": "r:1.0 g:1.0 b:1.0 a:1.0",
            "materialOffset": "x:1 y:1 z:1.0",
            "mesh": "asset/scene/map_icebergvillage/map_icebergvillage_fangwu_01.mesh",
            "name": "map_icebergvillage_fangwu_01.mesh",
            "needSync": "false",
            "partNavMeshType": "1",
            "position": "x:73.329948425293 y:26.9676609039307 z:10.810959815979",
            "restitution": "0.3",
            "rotation": "x:0 y:180 z:0",
            "scale": "x:1.5 y:1.5 z:1.5",
            "simpleEmissiveIntensity": "1.0",
            "templateId": "9115066156583518209",
            "useAnchor": "true",
            "useForCollision": "false"
          }
        },
        {
          "attributes": [],
          "class": "MeshPart",
          "customProperties": [],
          "properties": {
            "btsKey": "",
            "canAcceptShadow": "true",
            "canGenerateShadow": "true",
            "customShapeData": "",
            "density": "2.2",
            "discardAlpha": "0.0",
            "exists_baked_data": "false",
            "friction": "0.37",
            "id": "9112238967251550209",
            "lodData": {
              "lodModelItem": []
            },
            "massCenter": "x:-81.7523345947266 y:29.2132930755615 z:68.3368988037109",
            "materialAlpha": "1.0",
            "materialColor": "r:1.0 g:1.0 b:1.0 a:1.0",
            "materialOffset": "x:1 y:1 z:1.0",
            "mesh": "asset/scene/map_icebergvillage/g2069_icebergvillage_plants01.mesh",
            "name": "g2069_icebergvillage_plants01.mesh",
            "needSync": "false",
            "partNavMeshType": "1",
            "position": "x:-81.7523345947266 y:29.2132930755615 z:68.3368988037109",
            "restitution": "0.3",
            "rotation": "x:0 y:137.000015258789 z:0",
            "scale": "x:1.8 y:1.8 z:1.8",
            "simpleEmissiveIntensity": "1.0",
            "staticBatchNo": "1",
            "templateId": "9112238967251550209",
            "useAnchor": "true",
            "useForCollision": "false"
          }
        },
        {
          "attributes": [],
          "class": "MeshPart",
          "customProperties": [],
          "properties": {
            "btsKey": "",
            "canAcceptShadow": "true",
            "canGenerateShadow": "true",
            "customShapeData": "",
            "density": "2.2",
            "discardAlpha": "0.0",
            "exists_baked_data": "false",
            "friction": "0.37",
            "id": "9112235400856715265",
            "lodData": {
              "lodModelItem": []
            },
            "massCenter": "x:64.0490036010742 y:27.3775024414062 z:-17.6759948730469",
            "materialAlpha": "1.0",
            "materialColor": "r:1.0 g:1.0 b:1.0 a:1.0",
            "materialOffset": "x:1 y:1 z:1.0",
            "mesh": "asset/scene/map_icebergvillage/g2069_icebergvillage_plants02.mesh",
            "name": "g2069_icebergvillage_plants02.mesh",
            "needSync": "false",
            "partNavMeshType": "1",
            "position": "x:64.0490036010742 y:27.3775024414062 z:-17.6759948730469",
            "restitution": "0.3",
            "rotation": "x:0 y:0 z:0",
            "scale": "x:0.799999 y:0.799999 z:0.799999",
            "simpleEmissiveIntensity": "1.0",
            "staticBatchNo": "1",
            "templateId": "9112235400856715265",
            "useAnchor": "true",
            "useForCollision": "false"
          }
        },
        {
          "attributes": [],
          "class": "MeshPart",
          "customProperties": [],
          "properties": {
            "btsKey": "",
            "canAcceptShadow": "true",
            "canGenerateShadow": "true",
            "customShapeData": "",
            "density": "2.2",
            "discardAlpha": "0.0",
            "exists_baked_data": "false",
            "friction": "0.37",
            "id": "9112244798857887745",
            "lodData": {
              "lodModelItem": []
            },
            "massCenter": "x:25.4619789123535 y:6.09750270843506 z:-31.7480125427246",
            "materialAlpha": "1.0",
            "materialColor": "r:1.0 g:1.0 b:1.0 a:1.0",
            "materialOffset": "x:1 y:1 z:1.0",
            "mesh": "asset/scene/map_icebergvillage/g2069_icebergvillage_plants02.mesh",
            "name": "g2069_icebergvillage_plants02.mesh",
            "needSync": "false",
            "partNavMeshType": "1",
            "position": "x:25.4619789123535 y:6.09750270843506 z:-31.7480125427246",
            "restitution": "0.3",
            "rotation": "x:0 y:90 z:0",
            "scale": "x:1.2 y:1.2 z:1.2",
            "simpleEmissiveIntensity": "1.0",
            "staticBatchNo": "1",
            "templateId": "9112244798857887745",
            "useAnchor": "true",
            "useForCollision": "false"
          }
        },
        {
          "attributes": [],
          "class": "MeshPart",
          "customProperties": [],
          "properties": {
            "btsKey": "",
            "canAcceptShadow": "true",
            "canGenerateShadow": "true",
            "customShapeData": "",
            "density": "2.2",
            "discardAlpha": "0.0",
            "exists_baked_data": "false",
            "friction": "0.37",
            "id": "9112241665063239681",
            "lodData": {
              "lodModelItem": []
            },
            "massCenter": "x:-5.99898052215576 y:15.2742948532104 z:-21.3380031585693",
            "materialAlpha": "1.0",
            "materialColor": "r:1.0 g:1.0 b:1.0 a:1.0",
            "materialOffset": "x:1 y:1 z:1.0",
            "mesh": "asset/scene/map_icebergvillage/g2069_icebergvillage_plants01.mesh",
            "name": "g2069_icebergvillage_plants01.mesh",
            "needSync": "false",
            "partNavMeshType": "1",
            "position": "x:-5.99898052215576 y:15.2742948532104 z:-21.3380031585693",
            "restitution": "0.3",
            "rotation": "x:0 y:90 z:0",
            "simpleEmissiveIntensity": "1.0",
            "staticBatchNo": "1",
            "templateId": "9112241665063239681",
            "useAnchor": "true",
            "useForCollision": "false"
          }
        },
        {
          "attributes": [],
          "class": "MeshPart",
          "customProperties": [],
          "properties": {
            "btsKey": "",
            "canAcceptShadow": "true",
            "canGenerateShadow": "true",
            "customShapeData": "",
            "density": "2.2",
            "discardAlpha": "0.0",
            "exists_baked_data": "false",
            "friction": "0.37",
            "id": "9112280791744364545",
            "lodData": {
              "lodModelItem": []
            },
            "massCenter": "x:-126.185722351074 y:25.6632919311523 z:19.2404460906982",
            "materialAlpha": "1.0",
            "materialColor": "r:1.0 g:1.0 b:1.0 a:1.0",
            "materialOffset": "x:1 y:1 z:1.0",
            "mesh": "asset/scene/map_icebergvillage/g2069_icebergvillage_plants01.mesh",
            "name": "g2069_icebergvillage_plants01.mesh",
            "needSync": "false",
            "partNavMeshType": "1",
            "position": "x:-126.185722351074 y:25.6632919311523 z:19.2404460906982",
            "restitution": "0.3",
            "rotation": "x:0 y:0 z:0",
            "scale": "x:0.8 y:0.8 z:0.8",
            "simpleEmissiveIntensity": "1.0",
            "staticBatchNo": "1",
            "templateId": "9112280791744364545",
            "useAnchor": "true",
            "useForCollision": "false"
          }
        },
        {
          "attributes": [],
          "class": "MeshPart",
          "customProperties": [],
          "properties": {
            "btsKey": "",
            "canAcceptShadow": "true",
            "canGenerateShadow": "true",
            "customShapeData": "",
            "density": "2.2",
            "discardAlpha": "0.0",
            "exists_baked_data": "false",
            "friction": "0.37",
            "id": "9112272846009712641",
            "lodData": {
              "lodModelItem": []
            },
            "massCenter": "x:-24.6040191650391 y:-19.3775043487549 z:-97.2519836425781",
            "materialAlpha": "1.0",
            "materialColor": "r:1.0 g:1.0 b:1.0 a:1.0",
            "materialOffset": "x:1 y:1 z:1.0",
            "mesh": "asset/scene/map_icebergvillage/g2069_icebergvillage_plants02.mesh",
            "name": "g2069_icebergvillage_plants02.mesh",
            "needSync": "false",
            "partNavMeshType": "1",
            "position": "x:-24.6040191650391 y:-19.3775043487549 z:-97.2519836425781",
            "restitution": "0.3",
            "rotation": "x:0 y:0 z:0",
            "simpleEmissiveIntensity": "1.0",
            "staticBatchNo": "1",
            "templateId": "9112272846009712641",
            "useAnchor": "true",
            "useForCollision": "false"
          }
        },
        {
          "attributes": [],
          "class": "MeshPart",
          "customProperties": [],
          "properties": {
            "btsKey": "",
            "canAcceptShadow": "true",
            "canGenerateShadow": "true",
            "customShapeData": "",
            "density": "2.2",
            "discardAlpha": "0.0",
            "exists_baked_data": "false",
            "friction": "0.37",
            "id": "9112240803209101313",
            "lodData": {
              "lodModelItem": []
            },
            "massCenter": "x:21.4310092926025 y:19.5595035552979 z:-21.2819995880127",
            "materialAlpha": "1.0",
            "materialColor": "r:1.0 g:1.0 b:1.0 a:1.0",
            "materialOffset": "x:1 y:1 z:1.0",
            "mesh": "asset/scene/map_icebergvillage/g2069_icebergvillage_plants02.mesh",
            "name": "g2069_icebergvillage_plants02.mesh",
            "needSync": "false",
            "partNavMeshType": "1",
            "position": "x:21.4310092926025 y:19.5595035552979 z:-21.2819995880127",
            "restitution": "0.3",
            "rotation": "x:0 y:0 z:0",
            "scale": "x:0.799999 y:0.799999 z:0.799999",
            "simpleEmissiveIntensity": "1.0",
            "staticBatchNo": "1",
            "templateId": "9112240803209101313",
            "useAnchor": "true",
            "useForCollision": "false"
          }
        },
        {
          "attributes": [],
          "class": "MeshPart",
          "customProperties": [],
          "properties": {
            "btsKey": "",
            "canAcceptShadow": "true",
            "canGenerateShadow": "true",
            "customShapeData": "",
            "density": "2.2",
            "discardAlpha": "0.0",
            "exists_baked_data": "false",
            "friction": "0.37",
            "id": "9112212515607183361",
            "lodData": {
              "lodModelItem": []
            },
            "massCenter": "x:-25.1750011444092 y:41.1100006103516 z:-60.5650253295898",
            "materialAlpha": "1.0",
            "materialColor": "r:1.0 g:1.0 b:1.0 a:1.0",
            "materialOffset": "x:1 y:1 z:1.0",
            "mesh": "asset/scene/map_icebergvillage/g2069_icebergvillage_ice.mesh",
            "name": "g2069_icebergvillage_ice.mesh",
            "needSync": "false",
            "originAnchor": "true",
            "partNavMeshType": "1",
            "position": "x:-25.1750011444092 y:41.1100006103516 z:-60.5650253295898",
            "restitution": "0.3",
            "rotation": "x:0 y:0 z:0",
            "simpleEmissiveIntensity": "1.0",
            "templateId": "9112212515607183361",
            "useAnchor": "true",
            "useForCollision": "false"
          }
        },
        {
          "attributes": [],
          "class": "MeshPart",
          "customProperties": [],
          "properties": {
            "btsKey": "",
            "canAcceptShadow": "true",
            "canGenerateShadow": "true",
            "customShapeData": "",
            "density": "2.2",
            "discardAlpha": "0.0",
            "exists_baked_data": "false",
            "friction": "0.37",
            "id": "9112278929076584449",
            "lodData": {
              "lodModelItem": []
            },
            "massCenter": "x:65.5600051879883 y:-9.52570533752441 z:-35.6929321289062",
            "materialAlpha": "1.0",
            "materialColor": "r:1.0 g:1.0 b:1.0 a:1.0",
            "materialOffset": "x:1 y:1 z:1.0",
            "mesh": "asset/scene/map_icebergvillage/g2069_icebergvillage_plants01.mesh",
            "name": "g2069_icebergvillage_plants01.mesh",
            "needSync": "false",
            "partNavMeshType": "1",
            "position": "x:65.5600051879883 y:-9.52570533752441 z:-35.6929321289062",
            "restitution": "0.3",
            "rotation": "x:0 y:90 z:0",
            "simpleEmissiveIntensity": "1.0",
            "staticBatchNo": "1",
            "templateId": "9112278929076584449",
            "useAnchor": "true",
            "useForCollision": "false"
          }
        },
        {
          "attributes": [],
          "class": "MeshPart",
          "customProperties": [],
          "properties": {
            "btsKey": "",
            "canAcceptShadow": "true",
            "canGenerateShadow": "true",
            "customShapeData": "",
            "density": "2.2",
            "discardAlpha": "0.0",
            "exists_baked_data": "false",
            "friction": "0.37",
            "id": "9112218453238939649",
            "lodData": {
              "lodModelItem": []
            },
            "massCenter": "x:72.4580001831055 y:27.6252956390381 z:33.8919906616211",
            "materialAlpha": "1.0",
            "materialColor": "r:1.0 g:1.0 b:1.0 a:1.0",
            "materialOffset": "x:1 y:1 z:1.0",
            "mesh": "asset/scene/map_icebergvillage/g2069_icebergvillage_plants01.mesh",
            "name": "g2069_icebergvillage_plants01.mesh",
            "needSync": "false",
            "partNavMeshType": "1",
            "position": "x:72.4580001831055 y:27.6252956390381 z:33.8919906616211",
            "restitution": "0.3",
            "rotation": "x:0 y:0 z:0",
            "scale": "x:1.5 y:1.5 z:1.5",
            "simpleEmissiveIntensity": "1.0",
            "staticBatchNo": "1",
            "templateId": "9112218453238939649",
            "useAnchor": "true",
            "useForCollision": "false"
          }
        },
        {
          "attributes": [],
          "class": "MeshPart",
          "customProperties": [],
          "properties": {
            "btsKey": "",
            "canAcceptShadow": "true",
            "canGenerateShadow": "true",
            "customShapeData": "",
            "density": "2.2",
            "discardAlpha": "0.0",
            "exists_baked_data": "false",
            "friction": "0.37",
            "id": "9112236166626754561",
            "lodData": {
              "lodModelItem": []
            },
            "massCenter": "x:91.5469589233398 y:32.5794906616211 z:2.83100533485413",
            "materialAlpha": "1.0",
            "materialColor": "r:1.0 g:1.0 b:1.0 a:1.0",
            "materialOffset": "x:1 y:1 z:1.0",
            "mesh": "asset/scene/map_icebergvillage/g2069_icebergvillage_plants02.mesh",
            "name": "g2069_icebergvillage_plants02.mesh",
            "needSync": "false",
            "partNavMeshType": "1",
            "position": "x:91.5469589233398 y:32.5794906616211 z:2.83100533485413",
            "restitution": "0.3",
            "rotation": "x:0 y:180 z:0",
            "scale": "x:1.3 y:1.3 z:1.3",
            "simpleEmissiveIntensity": "1.0",
            "staticBatchNo": "1",
            "templateId": "9112236166626754561",
            "useAnchor": "true",
            "useForCollision": "false"
          }
        },
        {
          "attributes": [],
          "class": "MeshPart",
          "customProperties": [],
          "properties": {
            "btsKey": "",
            "canAcceptShadow": "true",
            "canGenerateShadow": "true",
            "customShapeData": "",
            "density": "2.2",
            "discardAlpha": "0.0",
            "exists_baked_data": "false",
            "friction": "0.37",
            "id": "9112450852238524417",
            "lodData": {
              "lodModelItem": []
            },
            "massCenter": "x:-4.59537124633789 y:-2.32177972793579 z:-66.629997253418",
            "materialAlpha": "1.0",
            "materialColor": "r:1.0 g:1.0 b:1.0 a:1.0",
            "materialOffset": "x:1 y:1 z:1.0",
            "mesh": "asset/scene/map_icebergvillage/g2069_icebergvillage_stone01.mesh",
            "name": "g2069_icebergvillage_stone01.mesh",
            "needSync": "false",
            "partNavMeshType": "1",
            "position": "x:-4.59537124633789 y:-2.32177972793579 z:-66.629997253418",
            "restitution": "0.3",
            "rotation": "x:0 y:142 z:0",
            "scale": "x:1.33605 y:1.33605 z:1.33605",
            "simpleEmissiveIntensity": "1.0",
            "staticBatchNo": "1",
            "templateId": "9112450852238524417",
            "useAnchor": "true",
            "useForCollision": "false"
          }
        },
        {
          "attributes": [],
          "class": "MeshPart",
          "customProperties": [],
          "properties": {
            "btsKey": "",
            "canAcceptShadow": "true",
            "canGenerateShadow": "true",
            "customShapeData": "",
            "density": "2.2",
            "discardAlpha": "0.0",
            "exists_baked_data": "false",
            "friction": "0.37",
            "id": "9112217997575749633",
            "lodData": {
              "lodModelItem": []
            },
            "massCenter": "x:14.0930032730103 y:15.6600313186646 z:-20.673999786377",
            "materialAlpha": "1.0",
            "materialColor": "r:1.0 g:1.0 b:1.0 a:1.0",
            "materialOffset": "x:1 y:1 z:1.0",
            "mesh": "asset/scene/map_icebergvillage/g2069_icebergvillage_plants03.mesh",
            "name": "g2069_icebergvillage_plants03.mesh",
            "needSync": "false",
            "partNavMeshType": "1",
            "position": "x:14.0930032730103 y:15.6600313186646 z:-20.673999786377",
            "restitution": "0.3",
            "rotation": "x:0 y:0 z:0",
            "simpleEmissiveIntensity": "1.0",
            "staticBatchNo": "1",
            "templateId": "9112217997575749633",
            "useAnchor": "true",
            "useForCollision": "false"
          }
        },
        {
          "attributes": [],
          "class": "MeshPart",
          "customProperties": [],
          "properties": {
            "btsKey": "",
            "canAcceptShadow": "true",
            "canGenerateShadow": "true",
            "customShapeData": "",
            "density": "2.2",
            "discardAlpha": "0.0",
            "exists_baked_data": "false",
            "friction": "0.37",
            "id": "9112451917327712257",
            "lodData": {
              "lodModelItem": []
            },
            "massCenter": "x:-1.3170211315155 y:2.9395055770874 z:-70.6629943847656",
            "materialAlpha": "1.0",
            "materialColor": "r:1.0 g:1.0 b:1.0 a:1.0",
            "materialOffset": "x:1 y:1 z:1.0",
            "mesh": "asset/scene/map_icebergvillage/g2069_icebergvillage_plants02.mesh",
            "name": "g2069_icebergvillage_plants02.mesh",
            "needSync": "false",
            "partNavMeshType": "1",
            "position": "x:-1.3170211315155 y:2.9395055770874 z:-70.6629943847656",
            "restitution": "0.3",
            "rotation": "x:0 y:0 z:0",
            "scale": "x:0.799999 y:0.799999 z:0.799999",
            "simpleEmissiveIntensity": "1.0",
            "staticBatchNo": "1",
            "templateId": "9112451917327712257",
            "useAnchor": "true",
            "useForCollision": "false"
          }
        },
        {
          "attributes": [],
          "class": "MeshPart",
          "customProperties": [],
          "properties": {
            "btsKey": "",
            "canAcceptShadow": "true",
            "canGenerateShadow": "true",
            "customShapeData": "",
            "density": "2.2",
            "discardAlpha": "0.0",
            "exists_baked_data": "false",
            "friction": "0.37",
            "id": "9112250799086813185",
            "lodData": {
              "lodModelItem": []
            },
            "massCenter": "x:-88.9049530029297 y:-12.0697135925293 z:-62.6079978942871",
            "materialAlpha": "1.0",
            "materialColor": "r:1.0 g:1.0 b:1.0 a:1.0",
            "materialOffset": "x:1 y:1 z:1.0",
            "mesh": "asset/scene/map_icebergvillage/g2069_icebergvillage_plants01.mesh",
            "name": "g2069_icebergvillage_plants01.mesh",
            "needSync": "false",
            "partNavMeshType": "1",
            "position": "x:-88.9049530029297 y:-12.0697135925293 z:-62.6079978942871",
            "restitution": "0.3",
            "rotation": "x:0 y:0 z:0",
            "simpleEmissiveIntensity": "1.0",
            "staticBatchNo": "1",
            "templateId": "9112250799086813185",
            "useAnchor": "true",
            "useForCollision": "false"
          }
        },
        {
          "attributes": [],
          "class": "MeshPart",
          "customProperties": [],
          "properties": {
            "btsKey": "",
            "canAcceptShadow": "true",
            "canGenerateShadow": "true",
            "customShapeData": "",
            "density": "2.2",
            "discardAlpha": "0.0",
            "exists_baked_data": "false",
            "friction": "0.37",
            "id": "9115068115616530433",
            "lodData": {
              "lodModelItem": []
            },
            "massCenter": "x:76.844841003418 y:26.5537414550781 z:-13.5051860809326",
            "materialAlpha": "1.0",
            "materialColor": "r:1.0 g:1.0 b:1.0 a:1.0",
            "materialOffset": "x:1 y:1 z:1.0",
            "mesh": "asset/scene/map_icebergvillage/map_icebergvillage_fangwu_02.mesh",
            "name": "map_icebergvillage_fangwu_02.mesh",
            "needSync": "false",
            "partNavMeshType": "1",
            "position": "x:76.844841003418 y:26.5537414550781 z:-13.5051860809326",
            "restitution": "0.3",
            "rotation": "x:0 y:-78.9999923706055 z:0",
            "scale": "x:1.5 y:1.5 z:1.5",
            "simpleEmissiveIntensity": "1.0",
            "staticBatchNo": "1",
            "templateId": "9115068115616530433",
            "useAnchor": "true",
            "useForCollision": "false"
          }
        },
        {
          "attributes": [],
          "class": "MeshPart",
          "customProperties": [],
          "properties": {
            "btsKey": "",
            "canAcceptShadow": "true",
            "canGenerateShadow": "true",
            "customShapeData": "",
            "density": "2.2",
            "discardAlpha": "0.0",
            "exists_baked_data": "false",
            "friction": "0.37",
            "id": "9112234575698378753",
            "lodData": {
              "lodModelItem": []
            },
            "massCenter": "x:81.68798828125 y:22.8255062103271 z:31.7230014801025",
            "materialAlpha": "1.0",
            "materialColor": "r:1.0 g:1.0 b:1.0 a:1.0",
            "materialOffset": "x:1 y:1 z:1.0",
            "mesh": "asset/scene/map_icebergvillage/g2069_icebergvillage_plants02.mesh",
            "name": "g2069_icebergvillage_plants02.mesh",
            "needSync": "false",
            "partNavMeshType": "1",
            "position": "x:81.68798828125 y:22.8255062103271 z:31.7230014801025",
            "restitution": "0.3",
            "rotation": "x:0 y:0 z:0",
            "scale": "x:1.2 y:1.2 z:1.2",
            "simpleEmissiveIntensity": "1.0",
            "staticBatchNo": "1",
            "templateId": "9112234575698378753",
            "useAnchor": "true",
            "useForCollision": "false"
          }
        },
        {
          "attributes": [],
          "class": "MeshPart",
          "customProperties": [],
          "properties": {
            "btsKey": "",
            "canAcceptShadow": "true",
            "canGenerateShadow": "true",
            "customShapeData": "",
            "density": "2.2",
            "discardAlpha": "0.0",
            "exists_baked_data": "false",
            "friction": "0.37",
            "id": "9112238967257219073",
            "lodData": {
              "lodModelItem": []
            },
            "massCenter": "x:-81.5565719604492 y:21.8425006866455 z:58.2002563476562",
            "materialAlpha": "1.0",
            "materialColor": "r:1.0 g:1.0 b:1.0 a:1.0",
            "materialOffset": "x:1 y:1 z:1.0",
            "mesh": "asset/scene/map_icebergvillage/g2069_icebergvillage_plants02.mesh",
            "name": "g2069_icebergvillage_plants02.mesh",
            "needSync": "false",
            "partNavMeshType": "1",
            "position": "x:-81.5565719604492 y:21.8425006866455 z:58.2002563476562",
            "restitution": "0.3",
            "rotation": "x:0 y:-42.9999847412109 z:0",
            "scale": "x:1.5 y:1.5 z:1.5",
            "simpleEmissiveIntensity": "1.0",
            "staticBatchNo": "1",
            "templateId": "9112238967257219073",
            "useAnchor": "true",
            "useForCollision": "false"
          }
        },
        {
          "attributes": [],
          "class": "MeshPart",
          "customProperties": [],
          "properties": {
            "btsKey": "",
            "canAcceptShadow": "true",
            "canGenerateShadow": "true",
            "customShapeData": "",
            "density": "2.2",
            "discardAlpha": "0.0",
            "exists_baked_data": "false",
            "friction": "0.37",
            "id": "9112241665069154305",
            "lodData": {
              "lodModelItem": []
            },
            "massCenter": "x:-13.7449951171875 y:12.8235006332397 z:-30.8950080871582",
            "materialAlpha": "1.0",
            "materialColor": "r:1.0 g:1.0 b:1.0 a:1.0",
            "materialOffset": "x:1 y:1 z:1.0",
            "mesh": "asset/scene/map_icebergvillage/g2069_icebergvillage_plants02.mesh",
            "name": "g2069_icebergvillage_plants02.mesh",
            "needSync": "false",
            "partNavMeshType": "1",
            "position": "x:-13.7449951171875 y:12.8235006332397 z:-30.8950080871582",
            "restitution": "0.3",
            "rotation": "x:0 y:180 z:0",
            "simpleEmissiveIntensity": "1.0",
            "staticBatchNo": "1",
            "templateId": "9112241665069154305",
            "useAnchor": "true",
            "useForCollision": "false"
          }
        },
        {
          "attributes": [],
          "class": "MeshPart",
          "customProperties": [],
          "properties": {
            "btsKey": "",
            "canAcceptShadow": "true",
            "canGenerateShadow": "true",
            "customShapeData": "",
            "density": "2.2",
            "discardAlpha": "0.0",
            "exists_baked_data": "false",
            "friction": "0.37",
            "id": "9115070123899420673",
            "lodData": {
              "lodModelItem": []
            },
            "massCenter": "x:11.2204523086548 y:28.5976600646973 z:53.2203483581543",
            "materialAlpha": "1.0",
            "materialColor": "r:1.0 g:1.0 b:1.0 a:1.0",
            "materialOffset": "x:1 y:1 z:1.0",
            "mesh": "asset/scene/map_icebergvillage/map_icebergvillage_fangwu_01.mesh",
            "name": "map_icebergvillage_fangwu_01.mesh",
            "needSync": "false",
            "partNavMeshType": "1",
            "position": "x:11.2204523086548 y:28.5976600646973 z:53.2203483581543",
            "restitution": "0.3",
            "rotation": "x:0 y:-164.999984741211 z:0",
            "scale": "x:1.5 y:1.5 z:1.5",
            "simpleEmissiveIntensity": "1.0",
            "templateId": "9115070123899420673",
            "useAnchor": "true",
            "useForCollision": "false"
          }
        },
        {
          "attributes": [],
          "class": "MeshPart",
          "customProperties": [],
          "properties": {
            "btsKey": "",
            "canAcceptShadow": "true",
            "canGenerateShadow": "true",
            "customShapeData": "",
            "density": "2.2",
            "discardAlpha": "0.0",
            "exists_baked_data": "false",
            "friction": "0.37",
            "id": "9112232467257344001",
            "lodData": {
              "lodModelItem": []
            },
            "massCenter": "x:25.209020614624 y:32.5372848510742 z:44.672004699707",
            "materialAlpha": "1.0",
            "materialColor": "r:1.0 g:1.0 b:1.0 a:1.0",
            "materialOffset": "x:1 y:1 z:1.0",
            "mesh": "asset/scene/map_icebergvillage/g2069_icebergvillage_plants01.mesh",
            "name": "g2069_icebergvillage_plants01.mesh",
            "needSync": "false",
            "partNavMeshType": "1",
            "position": "x:25.209020614624 y:32.5372848510742 z:44.672004699707",
            "restitution": "0.3",
            "rotation": "x:0 y:180 z:0",
            "simpleEmissiveIntensity": "1.0",
            "staticBatchNo": "1",
            "templateId": "9112232467257344001",
            "useAnchor": "true",
            "useForCollision": "false"
          }
        },
        {
          "attributes": [],
          "class": "MeshPart",
          "customProperties": [],
          "properties": {
            "btsKey": "",
            "canAcceptShadow": "true",
            "canGenerateShadow": "true",
            "customShapeData": "",
            "density": "2.2",
            "discardAlpha": "0.0",
            "exists_baked_data": "false",
            "friction": "0.37",
            "id": "9112249977770147841",
            "lodData": {
              "lodModelItem": []
            },
            "massCenter": "x:-68.5529708862305 y:1.66750359535217 z:-48.5559844970703",
            "materialAlpha": "1.0",
            "materialColor": "r:1.0 g:1.0 b:1.0 a:1.0",
            "materialOffset": "x:1 y:1 z:1.0",
            "mesh": "asset/scene/map_icebergvillage/g2069_icebergvillage_plants02.mesh",
            "name": "g2069_icebergvillage_plants02.mesh",
            "needSync": "false",
            "partNavMeshType": "1",
            "position": "x:-68.5529708862305 y:1.66750359535217 z:-48.5559844970703",
            "restitution": "0.3",
            "rotation": "x:0 y:180 z:0",
            "scale": "x:0.799999 y:0.799999 z:0.799999",
            "simpleEmissiveIntensity": "1.0",
            "staticBatchNo": "1",
            "templateId": "9112249977770147841",
            "useAnchor": "true",
            "useForCollision": "false"
          }
        },
        {
          "attributes": [],
          "class": "MeshPart",
          "customProperties": [],
          "properties": {
            "btsKey": "",
            "canAcceptShadow": "true",
            "canGenerateShadow": "true",
            "customShapeData": "",
            "density": "2.2",
            "discardAlpha": "0.0",
            "exists_baked_data": "false",
            "friction": "0.37",
            "id": "9112244798864523265",
            "lodData": {
              "lodModelItem": []
            },
            "massCenter": "x:42.5850143432617 y:9.72329998016357 z:-35.2190399169922",
            "materialAlpha": "1.0",
            "materialColor": "r:1.0 g:1.0 b:1.0 a:1.0",
            "materialOffset": "x:1 y:1 z:1.0",
            "mesh": "asset/scene/map_icebergvillage/g2069_icebergvillage_plants01.mesh",
            "name": "g2069_icebergvillage_plants01.mesh",
            "needSync": "false",
            "partNavMeshType": "1",
            "position": "x:42.5850143432617 y:9.72329998016357 z:-35.2190399169922",
            "restitution": "0.3",
            "rotation": "x:0 y:90 z:0",
            "scale": "x:1.3 y:1.3 z:1.3",
            "simpleEmissiveIntensity": "1.0",
            "staticBatchNo": "1",
            "templateId": "9112244798864523265",
            "useAnchor": "true",
            "useForCollision": "false"
          }
        },
        {
          "attributes": [],
          "class": "MeshPart",
          "customProperties": [],
          "properties": {
            "btsKey": "",
            "canAcceptShadow": "true",
            "canGenerateShadow": "true",
            "customShapeData": "",
            "density": "2.2",
            "discardAlpha": "0.0",
            "exists_baked_data": "false",
            "friction": "0.37",
            "id": "9112456443257864193",
            "lodData": {
              "lodModelItem": []
            },
            "massCenter": "x:31.2674827575684 y:-26.1257514953613 z:-99.0021286010742",
            "materialAlpha": "1.0",
            "materialColor": "r:1.0 g:1.0 b:1.0 a:1.0",
            "materialOffset": "x:1 y:1 z:1.0",
            "mesh": "asset/scene/map_icebergvillage/g2069_icebergvillage_stone01.mesh",
            "name": "g2069_icebergvillage_stone01.mesh",
            "needSync": "false",
            "partNavMeshType": "1",
            "position": "x:31.2674827575684 y:-26.1257514953613 z:-99.0021286010742",
            "restitution": "0.3",
            "rotation": "x:0 y:142 z:0",
            "scale": "x:2 y:2 z:2",
            "simpleEmissiveIntensity": "1.0",
            "staticBatchNo": "1",
            "templateId": "9112456443257864193",
            "useAnchor": "true",
            "useForCollision": "false"
          }
        },
        {
          "attributes": [],
          "class": "MeshPart",
          "customProperties": [],
          "properties": {
            "btsKey": "",
            "canAcceptShadow": "true",
            "canGenerateShadow": "true",
            "customShapeData": "",
            "density": "2.2",
            "discardAlpha": "0.0",
            "exists_baked_data": "false",
            "friction": "0.37",
            "id": "9112218365558456321",
            "lodData": {
              "lodModelItem": []
            },
            "massCenter": "x:17.6340026855469 y:20.9275035858154 z:29.1050090789795",
            "materialAlpha": "1.0",
            "materialColor": "r:1.0 g:1.0 b:1.0 a:1.0",
            "materialOffset": "x:1 y:1 z:1.0",
            "mesh": "asset/scene/map_icebergvillage/g2069_icebergvillage_plants02.mesh",
            "name": "g2069_icebergvillage_plants02.mesh",
            "needSync": "false",
            "partNavMeshType": "1",
            "position": "x:17.6340026855469 y:20.9275035858154 z:29.1050090789795",
            "restitution": "0.3",
            "rotation": "x:0 y:0 z:0",
            "simpleEmissiveIntensity": "1.0",
            "staticBatchNo": "1",
            "templateId": "9112218365558456321",
            "useAnchor": "true",
            "useForCollision": "false"
          }
        },
        {
          "attributes": [],
          "class": "MeshPart",
          "customProperties": [],
          "properties": {
            "btsKey": "",
            "canAcceptShadow": "true",
            "canGenerateShadow": "true",
            "customShapeData": "",
            "density": "2.2",
            "discardAlpha": "0.0",
            "exists_baked_data": "false",
            "friction": "0.37",
            "id": "9112273966160494593",
            "lodData": {
              "lodModelItem": []
            },
            "massCenter": "x:59.7460021972656 y:-17.0397090911865 z:-92.4419174194336",
            "materialAlpha": "1.0",
            "materialColor": "r:1.0 g:1.0 b:1.0 a:1.0",
            "materialOffset": "x:1 y:1 z:1.0",
            "mesh": "asset/scene/map_icebergvillage/g2069_icebergvillage_plants01.mesh",
            "name": "g2069_icebergvillage_plants01.mesh",
            "needSync": "false",
            "partNavMeshType": "1",
            "position": "x:59.7460021972656 y:-17.0397090911865 z:-92.4419174194336",
            "restitution": "0.3",
            "rotation": "x:0 y:90 z:0",
            "simpleEmissiveIntensity": "1.0",
            "staticBatchNo": "1",
            "templateId": "9112273966160494593",
            "useAnchor": "true",
            "useForCollision": "false"
          }
        },
        {
          "attributes": [],
          "class": "MeshPart",
          "customProperties": [],
          "properties": {
            "btsKey": "",
            "canAcceptShadow": "true",
            "canGenerateShadow": "true",
            "customShapeData": "",
            "density": "2.2",
            "discardAlpha": "0.0",
            "exists_baked_data": "false",
            "friction": "0.37",
            "id": "9115062461851451393",
            "lodData": {
              "lodModelItem": []
            },
            "massCenter": "x:29.2408485412598 y:24.6547889709473 z:22.5275402069092",
            "materialAlpha": "1.0",
            "materialColor": "r:1.0 g:1.0 b:1.0 a:1.0",
            "materialOffset": "x:1 y:1 z:1.0",
            "mesh": "asset/scene/map_icebergvillage/map_icebergvillage_fangwu_04.mesh",
            "name": "map_icebergvillage_fangwu_04.mesh",
            "needSync": "false",
            "partNavMeshType": "1",
            "position": "x:29.2408485412598 y:24.6547889709473 z:22.5275402069092",
            "restitution": "0.3",
            "rotation": "x:0 y:-166.999984741211 z:0",
            "scale": "x:1.5 y:1.5 z:1.5",
            "simpleEmissiveIntensity": "1.0",
            "staticBatchNo": "1",
            "templateId": "9115062461851451393",
            "useAnchor": "true",
            "useForCollision": "false"
          }
        },
        {
          "attributes": [],
          "class": "MeshPart",
          "customProperties": [],
          "properties": {
            "btsKey": "",
            "canAcceptShadow": "true",
            "canGenerateShadow": "true",
            "customShapeData": "",
            "density": "2.2",
            "discardAlpha": "0.0",
            "exists_baked_data": "false",
            "friction": "0.37",
            "id": "9112212535642439681",
            "lodData": {
              "lodModelItem": []
            },
            "massCenter": "x:-25.1750011444092 y:9.60220718383789 z:-51.0489883422852",
            "materialAlpha": "1.0",
            "materialColor": "r:1.0 g:1.0 b:1.0 a:1.0",
            "materialOffset": "x:1 y:1 z:1.0",
            "mesh": "asset/scene/map_icebergvillage/g2069_icebergvillage_snow.mesh",
            "name": "g2069_icebergvillage_snow.mesh",
            "needSync": "false",
            "originAnchor": "true",
            "partNavMeshType": "1",
            "position": "x:-25.1750011444092 y:9.60220718383789 z:-51.0489883422852",
            "restitution": "0.3",
            "rotation": "x:0 y:0 z:0",
            "simpleEmissiveIntensity": "1.0",
            "templateId": "9112212535642439681",
            "useAnchor": "true",
            "useForCollision": "false"
          }
        },
        {
          "attributes": [],
          "class": "MeshPart",
          "customProperties": [],
          "properties": {
            "btsKey": "",
            "canAcceptShadow": "true",
            "canGenerateShadow": "true",
            "customShapeData": "",
            "density": "2.2",
            "discardAlpha": "0.0",
            "exists_baked_data": "false",
            "friction": "0.37",
            "id": "9112250799117434881",
            "lodData": {
              "lodModelItem": []
            },
            "massCenter": "x:-46.5650062561035 y:-12.2065048217773 z:-62.3770065307617",
            "materialAlpha": "1.0",
            "materialColor": "r:1.0 g:1.0 b:1.0 a:1.0",
            "materialOffset": "x:1 y:1 z:1.0",
            "mesh": "asset/scene/map_icebergvillage/g2069_icebergvillage_plants02.mesh",
            "name": "g2069_icebergvillage_plants02.mesh",
            "needSync": "false",
            "partNavMeshType": "1",
            "position": "x:-46.5650062561035 y:-12.2065048217773 z:-62.3770065307617",
            "restitution": "0.3",
            "rotation": "x:0 y:90 z:0",
            "scale": "x:1.2 y:1.2 z:1.2",
            "simpleEmissiveIntensity": "1.0",
            "staticBatchNo": "1",
            "templateId": "9112250799117434881",
            "useAnchor": "true",
            "useForCollision": "false"
          }
        },
        {
          "attributes": [],
          "class": "MeshPart",
          "customProperties": [],
          "properties": {
            "btsKey": "",
            "canAcceptShadow": "true",
            "canGenerateShadow": "true",
            "customShapeData": "",
            "density": "2.2",
            "discardAlpha": "0.0",
            "exists_baked_data": "false",
            "friction": "0.37",
            "id": "9112286286183088129",
            "lodData": {
              "lodModelItem": []
            },
            "massCenter": "x:21.7540168762207 y:29.9822978973389 z:47.851993560791",
            "materialAlpha": "1.0",
            "materialColor": "r:1.0 g:1.0 b:1.0 a:1.0",
            "materialOffset": "x:1 y:1 z:1.0",
            "mesh": "asset/scene/map_icebergvillage/g2069_icebergvillage_plants01.mesh",
            "name": "g2069_icebergvillage_plants01.mesh",
            "needSync": "false",
            "partNavMeshType": "1",
            "position": "x:21.7540168762207 y:29.9822978973389 z:47.851993560791",
            "restitution": "0.3",
            "rotation": "x:0 y:0 z:0",
            "scale": "x:0.699999 y:0.699999 z:0.699999",
            "simpleEmissiveIntensity": "1.0",
            "staticBatchNo": "1",
            "templateId": "9112286286183088129",
            "useAnchor": "true",
            "useForCollision": "false"
          }
        },
        {
          "attributes": [],
          "class": "MeshPart",
          "customProperties": [],
          "properties": {
            "btsKey": "",
            "canAcceptShadow": "true",
            "canGenerateShadow": "true",
            "customShapeData": "",
            "density": "2.2",
            "discardAlpha": "0.0",
            "exists_baked_data": "false",
            "friction": "0.37",
            "id": "9112247208970616833",
            "lodData": {
              "lodModelItem": []
            },
            "massCenter": "x:16.7589797973633 y:2.9395055770874 z:-33.9250068664551",
            "materialAlpha": "1.0",
            "materialColor": "r:1.0 g:1.0 b:1.0 a:1.0",
            "materialOffset": "x:1 y:1 z:1.0",
            "mesh": "asset/scene/map_icebergvillage/g2069_icebergvillage_plants02.mesh",
            "name": "g2069_icebergvillage_plants02.mesh",
            "needSync": "false",
            "partNavMeshType": "1",
            "position": "x:16.7589797973633 y:2.9395055770874 z:-33.9250068664551",
            "restitution": "0.3",
            "rotation": "x:0 y:0 z:0",
            "scale": "x:0.799999 y:0.799999 z:0.799999",
            "simpleEmissiveIntensity": "1.0",
            "staticBatchNo": "1",
            "templateId": "9112247208970616833",
            "useAnchor": "true",
            "useForCollision": "false"
          }
        },
        {
          "attributes": [],
          "class": "MeshPart",
          "customProperties": [],
          "properties": {
            "btsKey": "",
            "canAcceptShadow": "true",
            "canGenerateShadow": "true",
            "customShapeData": "",
            "density": "2.2",
            "discardAlpha": "0.0",
            "exists_baked_data": "false",
            "friction": "0.37",
            "id": "9112233700734337025",
            "lodData": {
              "lodModelItem": []
            },
            "massCenter": "x:88.4580230712891 y:32.6593055725098 z:39.2699890136719",
            "materialAlpha": "1.0",
            "materialColor": "r:1.0 g:1.0 b:1.0 a:1.0",
            "materialOffset": "x:1 y:1 z:1.0",
            "mesh": "asset/scene/map_icebergvillage/g2069_icebergvillage_plants01.mesh",
            "name": "g2069_icebergvillage_plants01.mesh",
            "needSync": "false",
            "partNavMeshType": "1",
            "position": "x:88.4580230712891 y:32.6593055725098 z:39.2699890136719",
            "restitution": "0.3",
            "rotation": "x:0 y:180 z:0",
            "scale": "x:2 y:2 z:2",
            "simpleEmissiveIntensity": "1.0",
            "staticBatchNo": "1",
            "templateId": "9112233700734337025",
            "useAnchor": "true",
            "useForCollision": "false"
          }
        },
        {
          "attributes": [],
          "class": "MeshPart",
          "customProperties": [],
          "properties": {
            "btsKey": "",
            "canAcceptShadow": "true",
            "canGenerateShadow": "true",
            "customShapeData": "",
            "density": "2.2",
            "discardAlpha": "0.0",
            "exists_baked_data": "false",
            "friction": "0.37",
            "id": "9122151453772611585",
            "lodData": {
              "lodModelItem": []
            },
            "massCenter": "x:-91.4099731445312 y:-0.610496461391449 z:-21.8499946594238",
            "materialAlpha": "1.0",
            "materialColor": "r:1.0 g:1.0 b:1.0 a:1.0",
            "materialOffset": "x:1 y:1 z:1.0",
            "mesh": "asset/scene/map_icebergvillage/g2069_icebergvillage_plants02.mesh",
            "name": "g2069_icebergvillage_plants02.mesh",
            "needSync": "false",
            "partNavMeshType": "1",
            "position": "x:-91.4099731445312 y:-0.610496461391449 z:-21.8499946594238",
            "restitution": "0.3",
            "rotation": "x:0 y:90 z:0",
            "scale": "x:0.599999 y:0.6 z:0.599999",
            "simpleEmissiveIntensity": "1.0",
            "staticBatchNo": "",
            "templateId": "9122151453772611585",
            "useAnchor": "true",
            "useForCollision": "false"
          }
        },
        {
          "attributes": [],
          "class": "MeshPart",
          "customProperties": [],
          "properties": {
            "btsKey": "",
            "canAcceptShadow": "true",
            "canGenerateShadow": "true",
            "customShapeData": "",
            "density": "2.2",
            "discardAlpha": "0.0",
            "exists_baked_data": "false",
            "friction": "0.37",
            "id": "9122152139413569537",
            "lodData": {
              "lodModelItem": []
            },
            "massCenter": "x:-87.1435165405273 y:4.72030544281006 z:-20.2984371185303",
            "materialAlpha": "1.0",
            "materialColor": "r:1.0 g:1.0 b:1.0 a:1.0",
            "materialOffset": "x:1 y:1 z:1.0",
            "mesh": "asset/scene/map_icebergvillage/g2069_icebergvillage_plants01.mesh",
            "name": "g2069_icebergvillage_plants01.mesh",
            "needSync": "false",
            "partNavMeshType": "1",
            "position": "x:-87.1435165405273 y:4.72030544281006 z:-20.2984371185303",
            "restitution": "0.3",
            "rotation": "x:0 y:90 z:0",
            "simpleEmissiveIntensity": "1.0",
            "staticBatchNo": "1",
            "templateId": "9122152139413569537",
            "useAnchor": "true",
            "useForCollision": "false"
          }
        },
        {
          "attributes": [],
          "class": "MeshPart",
          "customProperties": [],
          "properties": {
            "btsKey": "",
            "canAcceptShadow": "true",
            "canGenerateShadow": "true",
            "customShapeData": "",
            "density": "2.2",
            "discardAlpha": "0.0",
            "exists_baked_data": "false",
            "friction": "0.37",
            "id": "9121790837663268865",
            "lodData": {
              "lodModelItem": []
            },
            "massCenter": "x:-15.5331478118896 y:31.9041328430176 z:-27.9038047790527",
            "materialAlpha": "0",
            "materialColor": "r:1.0 g:1.0 b:1.0 a:1.0",
            "materialOffset": "x:1 y:1 z:1.0",
            "mesh": "asset/scene/map_icebergvillage/g2069_icebergvillage_wall.mesh",
            "name": "g2069_icebergvillage_wall.mesh",
            "needSync": "false",
            "originAnchor": "true",
            "partNavMeshType": "1",
            "position": "x:-15.5331478118896 y:31.9041328430176 z:-27.9038047790527",
            "restitution": "0.3",
            "rotation": "x:0 y:0 z:0",
            "simpleEmissiveIntensity": "1.0",
            "templateId": "9121790837663268865",
            "useAnchor": "true",
            "useForCollision": "false"
          }
        },
        {
          "attributes": [],
          "class": "MeshPart",
          "customProperties": [],
          "properties": {
            "btsKey": "",
            "canAcceptShadow": "true",
            "canGenerateShadow": "true",
            "customShapeData": "",
            "density": "2.2",
            "discardAlpha": "0.0",
            "exists_baked_data": "false",
            "friction": "0.37",
            "id": "9122165571390881793",
            "lodData": {
              "lodModelItem": []
            },
            "massCenter": "x:-20.6269989013672 y:11.7652988433838 z:22.6279945373535",
            "materialAlpha": "1.0",
            "materialColor": "r:1.0 g:1.0 b:1.0 a:1.0",
            "materialOffset": "x:1 y:1 z:1.0",
            "mesh": "asset/scene/map_icebergvillage/g2069_icebergvillage_plants01.mesh",
            "name": "g2069_icebergvillage_plants01.mesh",
            "needSync": "false",
            "partNavMeshType": "1",
            "position": "x:-20.6269989013672 y:11.7652988433838 z:22.6279945373535",
            "restitution": "0.3",
            "rotation": "x:0 y:0 z:0",
            "scale": "x:1.5 y:1.5 z:1.5",
            "simpleEmissiveIntensity": "1.0",
            "staticBatchNo": "1",
            "templateId": "9122165571390881793",
            "useAnchor": "true",
            "useForCollision": "false"
          }
        }
      ],
      "class": "Folder",
      "customProperties": [],
      "properties": {
        "aclNames": [],
        "id": "9120605271241605121",
        "isDataSet": "false",
        "isVisible": "true",
        "name": "map",
        "useForCollision": "false"
      }
    },
    {
      "attributes": [],
      "class": "Folder",
      "customProperties": [],
      "properties": {
        "aclNames": [],
        "id": "9139066620442296321",
        "isDataSet": "true",
        "isVisible": "true",
        "name": "gameContent",
        "useForCollision": "false"
      }
    }
  ],
  "skyBox": [
    {
      "texture": [
        "@asset/Texture/SkyBox/skybox_icebergvillage/icebergvillage_right.png",
        "@asset/Texture/SkyBox/skybox_icebergvillage/icebergvillage_left.png",
        "@asset/Texture/SkyBox/skybox_icebergvillage/icebergvillage_top.png",
        "@asset/Texture/SkyBox/skybox_icebergvillage/icebergvillage_bottom.png",
        "@asset/Texture/SkyBox/skybox_icebergvillage/icebergvillage_back.png",
        "@asset/Texture/SkyBox/skybox_icebergvillage/icebergvillage_front.png"
      ]
    }
  ],
  "skyBoxMode": "static_display",
  "skyBoxRotate": {
    "x": 0,
    "y": 0,
    "z": 0
  },
  "skyBoxTexPixFmt": "RGBA8",
  "skyBoxTexSize": 512,
  "touchPosY": {
    "touchdownPosY": -30,
    "touchupPosY": 720
  },
  "useLod": false
}