{
  "attribute_pct": {
    "eleDamage": 0.1,
    "maxHp": 0.35,
    "maxMp": 0.2
  },
  "buffId": 38043,
  "buffName": "myplugin/gen_buff/skill_buff_38043",
  "childActor": {
    "actorName": "g2069_zuozhu_xuzuonenghu.actor",
    "pos": {
      "x": 0,
      "y": 0,
      "z": -0.5
    },
    "scale": "1.6"
  },
  "deadRemove": true,
  "needSave": false,
  "removeBuff": [
    "myplugin/gen_buff/skill_buff_38044"
  ],
  "resetSkill": {
    "skillList": [
      37044,
      2704
    ],
    "slotList": [
      4,
      8
    ]
  }
}